LICENSE
README.md
aws_clutter/__init__.py
aws_clutter/cli.py
aws_clutter/clutter/__init__.py
aws_clutter/clutter/debs.py
aws_clutter/clutter/ulbs.py
aws_clutter/data/ebs_pricing.json
aws_clutter/data/elb_pricing.json
aws_clutter/tools.py
aws_clutter-0.9.5.dist-info/entry_points.txt
aws_clutter-0.9.5.dist-info/LICENSE
aws_clutter-0.9.5.dist-info/WHEEL
aws_clutter-0.9.5.dist-info/METADATA
aws_clutter-0.9.5.dist-info/RECORD
