Metadata-Version: 2.1
Name: aws-clutter
Version: 0.9.5
Summary: monitor the cost of unused AWS resources
License: MIT
Author: Shinichi Urano
Author-email: s@urano.me
Requires-Python: >=3.7.10,<4
Classifier: License :: OSI Approved :: MIT License
Classifier: Programming Language :: Python :: 3
Classifier: Programming Language :: Python :: 3.10
Classifier: Programming Language :: Python :: 3.8
Classifier: Programming Language :: Python :: 3.9
Requires-Dist: boto3 (>=1.19.4,<2.0.0)
Requires-Dist: click (>=8.0.3,<9.0.0)
Requires-Dist: importlib-metadata (>=4.8.1,<5.0.0)
Requires-Dist: importlib-resources (>=5.3.0,<6.0.0)
Requires-Dist: pendulum (>=2.1.2,<3.0.0)
